LICENSE.txt
MANIFEST.in
README.md
pyproject.toml
setup.cfg
setup.py
src/dependency/__init__.py
src/dependency/manage.py
src/luci_utils.egg-info/PKG-INFO
src/luci_utils.egg-info/SOURCES.txt
src/luci_utils.egg-info/dependency_links.txt
src/luci_utils.egg-info/top_level.txt