Metadata-Version: 2.1
Name: luci-utils
Version: 0.0.1
Summary: short package description
Author: Charlie James
Author-email: charliejamescode@gmail.com
Classifier: Programming Language :: Python :: 3
Classifier: License :: OSI Approved :: MIT License
Classifier: Operating System :: OS Independent
Requires-Python: >=3.7
License-File: LICENSE.txt
